Ano_express/Ano_express.py
Ano_express/__init__.py
ano_express-0.0.5.1.dist-info/LICENSE
ano_express-0.0.5.1.dist-info/WHEEL
ano_express-0.0.5.1.dist-info/METADATA
ano_express-0.0.5.1.dist-info/RECORD
