Metadata-Version: 2.1
Name: ano-express
Version: 0.0.5.1
Summary: A package to access insecticide resistance gene expression meta analyse in Anopheles mosquitoes
License: MIT
Author: Sanjay Nagi
Author-email: sanjay.nagi@lstmed.ac.uk
Requires-Python: >=3.7.1,<3.10
Classifier: License :: OSI Approved :: MIT License
Classifier: Programming Language :: Python :: 3
Classifier: Programming Language :: Python :: 3.8
Classifier: Programming Language :: Python :: 3.9
Requires-Dist: numpy
Requires-Dist: pandas
Requires-Dist: plotly
Requires-Dist: scipy
Requires-Dist: seaborn
Requires-Dist: statsmodels
Requires-Dist: tqdm
